sectw/2017-11-14.csv
sectw/2018-08-14.csv
sectw/__init__.py
sectw/api.py
sectw/builder.py
sectw/util.py
sectw/database/__init__.py
sectw/database/config.py
sectw/database/model.py
sectw-18.12.1.dist-info/LICENSE.txt
sectw-18.12.1.dist-info/METADATA
sectw-18.12.1.dist-info/WHEEL
sectw-18.12.1.dist-info/top_level.txt
sectw-18.12.1.dist-info/RECORD
